{
      "products":[
            {
                  "id":1,
                  "productimage":"https://m.media-amazon.com/images/I/81mQztemBkL._AC_UL320_.jpg",
                  "producttitle":"Desk Office Chair",
                  "price":"3989",
                  "rating":"4",
                  "description":"This is  a well designed creafted products that will suit many needs in terms of quality,craftsmanship and aesthetics"
            },
            {
                  "id":2,
                  "productimage":"https://m.media-amazon.com/images/I/81yJVI6Za5L._AC_UL320_.jpg",
                  "producttitle":"Apex Chairs",
                  "price":"5262",
                  "rating":"4",
                  "description":"This is  a well designed creafted products that will suit many needs in terms of quality,craftsmanship and aesthetics"
            },
            {
                  "id":3,
                  "productimage":"https://m.media-amazon.com/images/I/51oPzSU4x5L._AC_UL320_.jpg",
                  "producttitle":"Jupiter Superb Office",
                  "price":"9590",
                  "rating":"4",
                  "description":"This is  a well designed creafted products that will suit many needs in terms of quality,craftsmanship and aesthetics"
            }
      ]


}